zbyte/__init__.py
zbyte/client.py
zbyte/config.py
zbyte/constants.py
zbyte/exceptions.py
zbyte/utils.py
zbyte-0.1.2.dist-info/licenses/LICENSE
zbyte-0.1.2.dist-info/METADATA
zbyte-0.1.2.dist-info/WHEEL
zbyte-0.1.2.dist-info/top_level.txt
zbyte-0.1.2.dist-info/RECORD
