Metadata-Version: 2.4
Name: zbyte
Version: 0.1.2
Summary: Python SDK for 0byte image generation and proof anchoring
Author-email: 0byte <nitinmewar28@gmail.com>
License: MIT
Project-URL: Homepage, https://www.0byte.tech
Project-URL: Source, https://github.com/0byte-lab/python-sdk
Keywords: ai,proof,solana,image verification,zero byte
Requires-Python: >=3.8
License-File: LICENSE
Requires-Dist: requests>=2.28
Requires-Dist: pydantic>=1.10
Requires-Dist: pillow
Requires-Dist: diffusers
Requires-Dist: transformers
Requires-Dist: torch
Requires-Dist: accelerate
Dynamic: license-file
